COPYING
LICENSE
MANIFEST.in
README.rst
ctqw_common
makefile
setup.py
./src/ctqwMPI.F90
docs/Makefile
docs/conf.py
docs/downloads.rst
docs/examples.rst
docs/fortran.rst
docs/index.rst
docs/installation.rst
docs/libctqw-MPI.rst
docs/make.bat
docs/pyCTQW.MPI.Graph.rst
docs/pyCTQW.MPI.Graph2P.rst
docs/pyCTQW.MPI.Graph3P.rst
docs/pyCTQW.MPI.GraphISO.rst
docs/pyCTQW.MPI.Line.rst
docs/pyCTQW.MPI.Line2P.rst
docs/pyCTQW.MPI.Line3P.rst
docs/pyCTQW.MPI.ctqw.rst
docs/pyCTQW.MPI.io.rst
docs/pyCTQW.MPI.plot.rst
docs/pyCTQW.MPI.rst
docs/quickstart.rst
docs/requirements.txt
docs/_templates/class.rst
docs/_templates/method.rst
docs/examples/1P_3cayley/1P_3cayley.rst
docs/examples/1P_3cayley/1p_3cayley_graph.png
docs/examples/1P_3cayley/1p_3cayley_nodes.png
docs/examples/1P_3cayley/1p_3cayley_plot.png
docs/examples/1P_3cayley/3cayley.png
docs/examples/1P_line/1P_line.rst
docs/examples/1P_line/1p_line_nodes.png
docs/examples/1P_line/1p_line_plot.png
docs/examples/1P_sr/1P_sr.rst
docs/examples/1P_sr/1p_sr_graph.png
docs/examples/1P_sr/1p_sr_plot.png
docs/examples/2P_3cayley/2P_3cayley.rst
docs/examples/2P_3cayley/2p_3cayley_ent.png
docs/examples/2P_3cayley/2p_3cayley_graph.png
docs/examples/2P_3cayley/2p_3cayley_node1.png
docs/examples/2P_3cayley/2p_3cayley_nodes_particle1.png
docs/examples/2P_3cayley/2p_3cayley_nodes_particle2.png
docs/examples/2P_3cayley/2p_3cayley_plot.png
docs/examples/2P_3cayley/3cayley.png
docs/examples/2P_line/2P_line.rst
docs/examples/2P_line/2p_line_ent.png
docs/examples/2P_line/2p_line_nodes.png
docs/examples/2P_line/2p_line_plot.png
docs/examples/2P_sr/2P_sr.rst
docs/examples/2P_sr/2p_sr_graph.png
docs/examples/2P_sr/2p_sr_plot.png
docs/examples/3P_3cayley/3P_3cayley.rst
docs/examples/3P_3cayley/3cayley.png
docs/examples/3P_3cayley/3p_3cayley_node1.png
docs/examples/3P_3cayley/3p_3cayley_nodes_particle1.png
docs/examples/3P_3cayley/3p_3cayley_nodes_particle3.png
docs/examples/3P_3cayley/3p_3cayley_plot.png
docs/examples/3P_line/3P_line.rst
pyCTQW.egg-info/PKG-INFO
pyCTQW.egg-info/SOURCES.txt
pyCTQW.egg-info/dependency_links.txt
pyCTQW.egg-info/requires.txt
pyCTQW.egg-info/top_level.txt
