Metadata-Version: 1.1
Name: pyCTQW
Version: 1.1.0
Summary: An MPI enabled CTQW simulator
Home-page: http://pyctqw.readthedocs.org
Author: Josh Izaac
Author-email: josh@iza.ac
License: GPLv3
Platform: UNKNOWN
Classifier: Development Status :: 5 - Production/Stable
Classifier: Environment :: Console
Classifier: Intended Audience :: Science/Research
Classifier: License :: OSI Approved :: GNU General Public License v3 (GPLv3)
Classifier: Natural Language :: English
Classifier: Operating System :: POSIX
Classifier: Operating System :: MacOS :: MacOS X
Classifier: Operating System :: POSIX :: Linux
Classifier: Programming Language :: Python
Classifier: Programming Language :: Fortran
Classifier: Topic :: Scientific/Engineering :: Physics
Provides: pyCTQW
